anomaly_detection_tool/__init__.py
anomaly_detection_tool/anomaly_detection_model.py
anomaly_detection_tool/data_processor.py
chainguard/__init__.py
chainguard/blockchain.py
chainguard/blockchain_logger.py
chainguard/data_transfer.py
chainguard/data_transformer.py
chainguard/encryption.py
chainguard/tests/__init__.py
chainguard/tests/test_blockchain.py
chainguard/tests/test_data_transfer.py
chainguard/tests/test_encryption.py
shodan_scanner/__init__.py
shodan_scanner/scanner.py
shodan_scanner/tests/__init__.py
shodan_scanner/tests/scann_network_test.py
visualisation/__init__.py
visualisation/chainguard_graph_db.py
chagu-0.1.3.dist-info/LICENSE
chagu-0.1.3.dist-info/METADATA
chagu-0.1.3.dist-info/WHEEL
chagu-0.1.3.dist-info/top_level.txt
chagu-0.1.3.dist-info/RECORD
