Metadata-Version: 2.1
Name: chagu
Version: 0.1.3
Summary: ChainGuard: A Secure Data Transformation and Transfer Protocol using Blockchain Technology
Home-page: https://github.com/taimax13/chainguard
Author: Talex maxim
Author-email: taimax13@gmail.com
Classifier: Programming Language :: Python :: 3
Classifier: License :: OSI Approved :: MIT License
Classifier: Operating System :: OS Independent
Requires-Python: >=3.6
License-File: LICENSE
Requires-Dist: cryptography
